README.rst
darkened.zip
screenshot.png
setup.py
docs/HISTORY.txt
docs/INSTALL.txt
docs/LICENSE.GPL
docs/LICENSE.txt
plonetheme/__init__.py
plonetheme.darkened.egg-info/PKG-INFO
plonetheme.darkened.egg-info/SOURCES.txt
plonetheme.darkened.egg-info/dependency_links.txt
plonetheme.darkened.egg-info/entry_points.txt
plonetheme.darkened.egg-info/namespace_packages.txt
plonetheme.darkened.egg-info/requires.txt
plonetheme.darkened.egg-info/top_level.txt
plonetheme/darkened/__init__.py
plonetheme/darkened/configure.zcml
plonetheme/darkened/profiles/default/metadata.xml
plonetheme/darkened/profiles/default/theme.xml
plonetheme/darkened/static/default.css
plonetheme/darkened/static/index.html
plonetheme/darkened/static/license.txt
plonetheme/darkened/static/manifest.cfg
plonetheme/darkened/static/rules.xml
plonetheme/darkened/static/images/img1.gif
plonetheme/darkened/static/images/img2.gif
plonetheme/darkened/static/images/img3.gif
plonetheme/darkened/static/images/img4.gif
plonetheme/darkened/static/images/img5.gif
plonetheme/darkened/static/images/img6.jpg
plonetheme/darkened/static/images/img7.jpg